LICENSE
MANIFEST.in
README.rst
setup.cfg
setup.py
docs/Makefile
docs/authors.rst
docs/conf.py
docs/contributing.rst
docs/history.rst
docs/index.rst
docs/installation.rst
docs/make.bat
docs/readme.rst
docs/usage.rst
tenv/__init__.py
tenv/_environ.py
tenv/_initialize.py
tenv/_read_dot_env.py
tenv.egg-info/PKG-INFO
tenv.egg-info/SOURCES.txt
tenv.egg-info/dependency_links.txt
tenv.egg-info/not-zip-safe
tenv.egg-info/top_level.txt
tests/__init__.py
tests/test_read_dot_env.py
tests/test_tenv.py