Metadata-Version: 1.1
Name: tenv
Version: 0.1.0
Summary: tenv - Typed Environment Variables
Home-page: https://github.com/mkurnikov/tenv
Author: Maxim Kurnikov
Author-email: maxim.kurnikov@gmail.com
License: ISCL
Keywords: tenv
Platform: UNKNOWN
Classifier: Development Status :: 2 - Pre-Alpha
Classifier: Intended Audience :: Developers
Classifier: License :: OSI Approved :: ISC License (ISCL)
Classifier: Natural Language :: English
Classifier: Programming Language :: Python :: 3.5
